<?xml version="1.0" encoding="utf-8"?>
<Menu>
  <Axis>Y</Axis>
  <Effects>FadeEffect</Effects>
  <Spacing>
    <X>0</X>
    <Y>10</Y>
  </Spacing>
  <Alignment>
    <X>0</X>
    <Y>0</Y>
  </Alignment>

  <Item>
    <LinkType>Screen</LinkType> 
    <LinkID>GameplayScreen</LinkID>
    <Image>
      <TextColor>
        <R>100</R>
        <G>100</G>
        <B>100</B>
        <A>255</A>
      </TextColor>
      <Path>Misc/testtube_button</Path>
      <Text>New Game</Text>
    </Image>
  </Item>

  <Item>
    <LinkType>Menu</LinkType> 
    <LinkID>Content/Load/Menu/ComingSoonMenu.xml</LinkID>
    <Image>
      <TextColor>
        <R>100</R>
        <G>100</G>
        <B>100</B>
        <A>255</A>
      </TextColor>
      <Path>Misc/testtube_button</Path>
      <Text>Load Game</Text>
    </Image>
  </Item>

  <Item>
    <LinkType>Screen</LinkType> 
    <LinkID>ControlScreen</LinkID>
    <Image>
      <TextColor>
        <R>100</R>
        <G>100</G>
        <B>100</B>
        <A>255</A>
      </TextColor>
      <Path>Misc/testtube_button</Path>
      <Text>Controls</Text>
    </Image>
  </Item>

  <Item>
    <LinkType>Menu</LinkType> 
    <LinkID>Content/Load/Menu/CreditsMenu.xml</LinkID>
    <Image>
      <TextColor>
        <R>100</R>
        <G>100</G>
        <B>100</B>
        <A>255</A>
      </TextColor>
      <Path>Misc/testtube_button</Path>
      <Text>Credits</Text>
    </Image>
  </Item>
</Menu>
